RPnickAPI.py
rpnickapi-1.1.0.dist-info/METADATA
rpnickapi-1.1.0.dist-info/WHEEL
rpnickapi-1.1.0.dist-info/RECORD
